souperscraper/__init__.py
souperscraper/_version.py
souperscraper/getchromedriver.py
souperscraper/souperscraper.py
souperscraper-1.0.2.dist-info/LICENSE
souperscraper-1.0.2.dist-info/METADATA
souperscraper-1.0.2.dist-info/WHEEL
souperscraper-1.0.2.dist-info/entry_points.txt
souperscraper-1.0.2.dist-info/top_level.txt
souperscraper-1.0.2.dist-info/RECORD
