Metadata-Version: 2.1
Name: souperscraper
Version: 1.0.2
Summary: A simple web scraper base combining Beautiful Soup and Selenium
Home-page: https://github.com/LucasFaudman/souper-scraper.git
Author: Lucas Faudman
Author-email: Lucas Faudman <lucasfaudman@gmail.com>
License: MIT License
Project-URL: Homepage, https://github.com/LucasFaudman/souper-scraper.git
Project-URL: Repository, https://github.com/LucasFaudman/souper-scraper.git
Keywords: web-scraping,scraping,easy,beautifulsoup4,beautifulsoup,bs4,selenium,selenium-webdriver
Classifier: Intended Audience :: Developers
Classifier: Intended Audience :: Information Technology
Classifier: License :: OSI Approved :: MIT License
Classifier: Operating System :: OS Independent
Classifier: Programming Language :: Python
Classifier: Programming Language :: Python :: 3
Classifier: Programming Language :: Python :: 3.8
Classifier: Programming Language :: Python :: 3.9
Classifier: Programming Language :: Python :: 3.10
Classifier: Programming Language :: Python :: 3.11
Classifier: Topic :: Software Development :: Libraries :: Python Modules
Classifier: Topic :: Software Development :: Libraries :: Application Frameworks
Classifier: Topic :: Internet :: WWW/HTTP :: Indexing/Search
Requires-Python: >=3.8
License-File: LICENSE
Requires-Dist: selenium
Requires-Dist: beautifulsoup4
Requires-Dist: requests
